doconce_lexer.py
pygments_doconce-1.0.2.dist-info/LICENSE
pygments_doconce-1.0.2.dist-info/METADATA
pygments_doconce-1.0.2.dist-info/WHEEL
pygments_doconce-1.0.2.dist-info/entry_points.txt
pygments_doconce-1.0.2.dist-info/top_level.txt
pygments_doconce-1.0.2.dist-info/RECORD
