Metadata-Version: 2.1
Name: pygments-doconce
Version: 1.0.2
Summary: Distributed publication management system
Home-page: https://github.com/doconce/pygments-doconce
Author: Hans Petter Langtangen
Author-email: hpl@simula.no
Maintainer: Alessandro Marin
Maintainer-email: alessandro.marin@fys.uio.no
License: BSD
Keywords: pygments doconce lexer
Platform: UNKNOWN
Classifier: Development Status :: 5 - Production/Stable
Classifier: Environment :: Plugins
Classifier: Intended Audience :: Developers
Classifier: License :: OSI Approved :: BSD License
Classifier: Operating System :: OS Independent
Classifier: Programming Language :: Python :: 2
Classifier: Programming Language :: Python :: 3
